{"blockName": "DARINGBADI", "blockID": "2408018", "schoolID": "018DD", "schoolName": "U G GOVT NODAL HIGH SCHOOL, BUDAGUDA", "udise": "21210303903", "teacherCount": "8", "teacherList": [{"teacherID": "BEN9289018DD", "teacherName": "BENUDHARA BEHERA", "teacherPost": "Faculty", "UserUN": "BEN9289018DD", "UserPWD": "ss123", "ClassDetails": {"class": 10, "section": null, "subject": "Mathematics"}}, {"teacherID": "MAN8356018DD", "teacherName": "MANOJ BHOI", "teacherPost": "Faculty", "UserUN": "MAN8356018DD", "UserPWD": "ss123", "ClassDetails": {"class": 10, "section": null, "subject": "English"}}, {"teacherID": "SHY3705018DD", "teacherName": "SHYAMA SUNDAR SAHOO", "teacherPost": "Faculty", "UserUN": "SHY3705018DD", "UserPWD": "ss123", "ClassDetails": {"class": 10, "section": null, "subject": "Science"}}, {"teacherID": "BAM7491018DD", "teacherName": "BAMA CHANDRA PRADHAN", "teacherPost": "Faculty", "UserUN": "BAM7491018DD", "UserPWD": "ss123", "ClassDetails": {"class": 10, "section": null, "subject": "Sanskrit"}}, {"teacherID": "SAG4060018DD", "teacherName": "SAGNIKA SETHI", "teacherPost": "Faculty", "UserUN": "SAG4060018DD", "UserPWD": "ss123", "ClassDetails": {"class": 10, "section": null, "subject": "Mathematics"}}, {"teacherID": "BHA2867018DD", "teacherName": "BHAGBAN NAIK", "teacherPost": "Faculty", "UserUN": "BHA2867018DD", "UserPWD": "ss123", "ClassDetails": {"class": 10, "section": null, "subject": "History"}}, {"teacherID": "SUC1566018DD", "teacherName": "SUCHISMITA PRADHAN", "teacherPost": "Faculty", "UserUN": "SUC1566018DD", "UserPWD": "ss123", "ClassDetails": {"class": 10, "section": null, "subject": "Mathematics"}}, {"teacherID": "BRA2140018DD", "teacherName": "BRAJASUNDAR BEHERDALAI", "teacherPost": "Faculty", "UserUN": "BRA2140018DD", "UserPWD": "ss123", "ClassDetails": {"class": 10, "section": null, "subject": "Geography"}}]}