{"blockName": "ANANDAPUR", "blockID": "2403008", "schoolID": "204CC", "schoolName": "S.N Govt. High School,Padmapur", "udise": "21061400204", "studentCount": "62", "studentList": [{"UIN": "22204CC0002", "CNAME": "ADYASA SAHOO", "FNAME": "SANATAN SAHOO", "MNAME": "SANJULATA SAHOO", "SEX": "FEMALE", "DOB": "03/05/2007", "CAT": "OBC", "FL_TMRK": "92", "SL_TMRK": "83", "TL_TMRK": "92", "MTH_TMRK": "53", "GSC_TMRK": "79", "SSC_TMRK": "77", "GTOTAL": 476.0, "RES_GRADE": "B1", "FL_NAME": "FLO", "SL_NAME": "SLE", "tL_NAME": "TLS", "award_flag": null, "NFSA/SFSA": null, "bankDetails": null}, {"UIN": "22204CC0003", "CNAME": "ALOK KUMAR GHADEI", "FNAME": "RABINDRA GHADEI", "MNAME": "PAKANA GHADEI", "SEX": "MALE", "DOB": "03/02/2007", "CAT": "OBC", "FL_TMRK": "67", "SL_TMRK": "69", "TL_TMRK": "73", "MTH_TMRK": "49", "GSC_TMRK": "72", "SSC_TMRK": "65", "GTOTAL": 395.0, "RES_GRADE": "B2", "FL_NAME": "FLO", "SL_NAME": "SLE", "tL_NAME": "TLS", "award_flag": null, "NFSA/SFSA": null, "bankDetails": null}, {"UIN": "22204CC0004", "CNAME": "AMIYA RANJAN DAS", "FNAME": "RANGADHAR DAS", "MNAME": "MINATI DAS", "SEX": "MALE", "DOB": "20/05/2006", "CAT": "OBC", "FL_TMRK": "81", "SL_TMRK": "48", "TL_TMRK": "95", "MTH_TMRK": "45", "GSC_TMRK": "66", "SSC_TMRK": "71", "GTOTAL": 406.0, "RES_GRADE": "B2", "FL_NAME": "FLO", "SL_NAME": "SLE", "tL_NAME": "TLS", "award_flag": null, "NFSA/SFSA": null, "bankDetails": null}, {"UIN": "22204CC0008", "CNAME": "BABU KHATUA", "FNAME": "KATHI KHATUA", "MNAME": "KANCHANA KHATUA", "SEX": "MALE", "DOB": "25/11/2006", "CAT": "ST", "FL_TMRK": "20", "SL_TMRK": "23", "TL_TMRK": "15", "MTH_TMRK": "22", "GSC_TMRK": "24", "SSC_TMRK": "20", "GTOTAL": 124.0, "RES_GRADE": "F", "FL_NAME": "FLO", "SL_NAME": "SLE", "tL_NAME": "TLS", "award_flag": null, "NFSA/SFSA": null, "bankDetails": null}, {"UIN": "22204CC0009", "CNAME": "BARSARANI NAHAK", "FNAME": "PANCHANANA NAHAK", "MNAME": "HEMALATA NAHAK", "SEX": "FEMALE", "DOB": "10/02/2006", "CAT": "ST", "FL_TMRK": "55", "SL_TMRK": "41", "TL_TMRK": "52", "MTH_TMRK": "48", "GSC_TMRK": "55", "SSC_TMRK": "56", "GTOTAL": 307.0, "RES_GRADE": "C", "FL_NAME": "FLO", "SL_NAME": "SLE", "tL_NAME": "TLS", "award_flag": null, "NFSA/SFSA": null, "bankDetails": null}, {"UIN": "22204CC0010", "CNAME": "BHABANI SANKAR SAHOO", "FNAME": "SUKADEV SAHOO", "MNAME": "CHANDRABATI SAHOO", "SEX": "MALE", "DOB": "13/11/2006", "CAT": "OBC", "FL_TMRK": "97", "SL_TMRK": "96", "TL_TMRK": "99", "MTH_TMRK": "71", "GSC_TMRK": "93", "SSC_TMRK": "89", "GTOTAL": 545.0, "RES_GRADE": "A1", "FL_NAME": "FLO", "SL_NAME": "SLE", "tL_NAME": "TLS", "award_flag": null, "NFSA/SFSA": null, "bankDetails": null}, {"UIN": "22204CC0014", "CNAME": "BIJU DEHURI", "FNAME": "PURNA CHANDRA DEHURI", "MNAME": "BHABINI DEHURI", "SEX": "MALE", "DOB": "24/05/2006", "CAT": "ST", "FL_TMRK": "81", "SL_TMRK": "54", "TL_TMRK": "72", "MTH_TMRK": "51", "GSC_TMRK": "59", "SSC_TMRK": "53", "GTOTAL": 370.0, "RES_GRADE": "B2", "FL_NAME": "FLO", "SL_NAME": "SLE", "tL_NAME": "TLS", "award_flag": null, "NFSA/SFSA": null, "bankDetails": null}, {"UIN": "22204CC0015", "CNAME": "BIKRAM DEHURY", "FNAME": "BARINI DEHURY", "MNAME": "SABITRI DEHURY", "SEX": "MALE", "DOB": "08/11/2006", "CAT": "ST", "FL_TMRK": "73", "SL_TMRK": "66", "TL_TMRK": "66", "MTH_TMRK": "57", "GSC_TMRK": "64", "SSC_TMRK": "72", "GTOTAL": 398.0, "RES_GRADE": "B2", "FL_NAME": "FLO", "SL_NAME": "SLE", "tL_NAME": "TLS", "award_flag": null, "NFSA/SFSA": null, "bankDetails": null}, {"UIN": "22204CC0016", "CNAME": "BIKRAM SAHOO", "FNAME": "ARUNA SAHOO", "MNAME": "MOTI SAHOO", "SEX": "MALE", "DOB": "15/01/2007", "CAT": "OBC", "FL_TMRK": "82", "SL_TMRK": "49", "TL_TMRK": "65", "MTH_TMRK": "53", "GSC_TMRK": "54", "SSC_TMRK": "53", "GTOTAL": 356.0, "RES_GRADE": "C", "FL_NAME": "FLO", "SL_NAME": "SLE", "tL_NAME": "TLS", "award_flag": null, "NFSA/SFSA": null, "bankDetails": null}, {"UIN": "22204CC0020", "CNAME": "BISWAJIT BARIK", "FNAME": "SURENDRA BARIK", "MNAME": "BABITA BARIK", "SEX": "MALE", "DOB": "21/01/2007", "CAT": "OBC", "FL_TMRK": "69", "SL_TMRK": "60", "TL_TMRK": "91", "MTH_TMRK": "52", "GSC_TMRK": "58", "SSC_TMRK": "58", "GTOTAL": 388.0, "RES_GRADE": "B2", "FL_NAME": "FLO", "SL_NAME": "SLE", "tL_NAME": "TLS", "award_flag": null, "NFSA/SFSA": null, "bankDetails": null}, {"UIN": "22204CC0021", "CNAME": "DEEPAK KUMAR GHADEI", "FNAME": "SACHIT CHANDRA GHADEI", "MNAME": "SUBASINI GHADEI", "SEX": "MALE", "DOB": "18/01/2007", "CAT": "OBC", "FL_TMRK": "95", "SL_TMRK": "88", "TL_TMRK": "99", "MTH_TMRK": "78", "GSC_TMRK": "89", "SSC_TMRK": "90", "GTOTAL": 539.0, "RES_GRADE": "A2", "FL_NAME": "FLO", "SL_NAME": "SLE", "tL_NAME": "TLS", "award_flag": null, "NFSA/SFSA": null, "bankDetails": null}, {"UIN": "22204CC0022", "CNAME": "DEEPAK SAHOO", "FNAME": "ATULA SAHOO", "MNAME": "ARATI SAHOO", "SEX": "MALE", "DOB": "26/02/2007", "CAT": "OBC", "FL_TMRK": "68", "SL_TMRK": "73", "TL_TMRK": "88", "MTH_TMRK": "60", "GSC_TMRK": "80", "SSC_TMRK": "85", "GTOTAL": 454.0, "RES_GRADE": "B1", "FL_NAME": "FLO", "SL_NAME": "SLE", "tL_NAME": "TLS", "award_flag": null, "NFSA/SFSA": null, "bankDetails": null}, {"UIN": "22204CC0026", "CNAME": "JAGAN SAHOO", "FNAME": "NARESH CHANDRA SAHOO", "MNAME": "MINI SAHOO", "SEX": "MALE", "DOB": "28/10/2006", "CAT": "OBC", "FL_TMRK": "58", "SL_TMRK": "51", "TL_TMRK": "49", "MTH_TMRK": "48", "GSC_TMRK": "55", "SSC_TMRK": "50", "GTOTAL": 311.0, "RES_GRADE": "C", "FL_NAME": "FLO", "SL_NAME": "SLE", "tL_NAME": "TLS", "award_flag": null, "NFSA/SFSA": null, "bankDetails": null}, {"UIN": "22204CC0027", "CNAME": "KALANDI BARIK", "FNAME": "NARI BARIK", "MNAME": "BHAMA BARIK", "SEX": "MALE", "DOB": "17/03/2007", "CAT": "OBC", "FL_TMRK": "53", "SL_TMRK": "68", "TL_TMRK": "62", "MTH_TMRK": "48", "GSC_TMRK": "48", "SSC_TMRK": "67", "GTOTAL": 346.0, "RES_GRADE": "C", "FL_NAME": "FLO", "SL_NAME": "SLE", "tL_NAME": "TLS", "award_flag": null, "NFSA/SFSA": null, "bankDetails": null}, {"UIN": "22204CC0028", "CNAME": "KHAGESWAR BHOL", "FNAME": "SHIBA BHOL", "MNAME": "USHARANI BHOL", "SEX": "MALE", "DOB": "11/07/2006", "CAT": "OBC", "FL_TMRK": "51", "SL_TMRK": "42", "TL_TMRK": "50", "MTH_TMRK": "41", "GSC_TMRK": "59", "SSC_TMRK": "48", "GTOTAL": 291.0, "RES_GRADE": "D", "FL_NAME": "FLO", "SL_NAME": "SLE", "tL_NAME": "TLS", "award_flag": null, "NFSA/SFSA": null, "bankDetails": null}, {"UIN": "22204CC0032", "CNAME": "LIPA NAHAK", "FNAME": "NISHAKAR NAHAK", "MNAME": "SUMA NAHAK", "SEX": "FEMALE", "DOB": "12/01/2007", "CAT": "ST", "FL_TMRK": "44", "SL_TMRK": "50", "TL_TMRK": "54", "MTH_TMRK": "47", "GSC_TMRK": "51", "SSC_TMRK": "49", "GTOTAL": 295.0, "RES_GRADE": "D", "FL_NAME": "FLO", "SL_NAME": "SLE", "tL_NAME": "TLS", "award_flag": null, "NFSA/SFSA": null, "bankDetails": null}, {"UIN": "22204CC0033", "CNAME": "LIPU SAHOO", "FNAME": "DURYODHAN SAHOO", "MNAME": "PRAMILA SAHOO", "SEX": "MALE", "DOB": "02/02/2007", "CAT": "OBC", "FL_TMRK": "88", "SL_TMRK": "62", "TL_TMRK": "99", "MTH_TMRK": "56", "GSC_TMRK": "66", "SSC_TMRK": "82", "GTOTAL": 453.0, "RES_GRADE": "B1", "FL_NAME": "FLO", "SL_NAME": "SLE", "tL_NAME": "TLS", "award_flag": null, "NFSA/SFSA": null, "bankDetails": null}, {"UIN": "22204CC0034", "CNAME": "MAMATA DEHURI", "FNAME": "CHAUDHURY DEHURI", "MNAME": "CHANCHALLA DEHURI", "SEX": "FEMALE", "DOB": "20/03/2006", "CAT": "ST", "FL_TMRK": "47", "SL_TMRK": "40", "TL_TMRK": "51", "MTH_TMRK": "48", "GSC_TMRK": "48", "SSC_TMRK": "49", "GTOTAL": 283.0, "RES_GRADE": "D", "FL_NAME": "FLO", "SL_NAME": "SLE", "tL_NAME": "TLS", "award_flag": null, "NFSA/SFSA": null, "bankDetails": null}, {"UIN": "22204CC0038", "CNAME": "RAJENDRA BEHERA", "FNAME": "PRAHALLAD BEHERA", "MNAME": "JAYANTI BEHERA", "SEX": "MALE", "DOB": "28/05/2006", "CAT": "OBC", "FL_TMRK": "83", "SL_TMRK": "42", "TL_TMRK": "95", "MTH_TMRK": "54", "GSC_TMRK": "56", "SSC_TMRK": "70", "GTOTAL": 400.0, "RES_GRADE": "B2", "FL_NAME": "FLO", "SL_NAME": "SLE", "tL_NAME": "TLS", "award_flag": null, "NFSA/SFSA": null, "bankDetails": null}, {"UIN": "22204CC0039", "CNAME": "RAKHI NAHAK", "FNAME": "HADIBANDHU NAHAK", "MNAME": "RAIKA NAHAK", "SEX": "FEMALE", "DOB": "17/10/2006", "CAT": "ST", "FL_TMRK": "49", "SL_TMRK": "30", "TL_TMRK": "53", "MTH_TMRK": "54", "GSC_TMRK": "51", "SSC_TMRK": "46", "GTOTAL": 283.0, "RES_GRADE": "D", "FL_NAME": "FLO", "SL_NAME": "SLE", "tL_NAME": "TLS", "award_flag": null, "NFSA/SFSA": null, "bankDetails": null}, {"UIN": "22204CC0040", "CNAME": "SABITA KHATUA", "FNAME": "BABANA KHATUA", "MNAME": "BASANTI KHATUA", "SEX": "FEMALE", "DOB": "20/09/2006", "CAT": "ST", "FL_TMRK": "48", "SL_TMRK": "40", "TL_TMRK": "54", "MTH_TMRK": "53", "GSC_TMRK": "53", "SSC_TMRK": "54", "GTOTAL": 302.0, "RES_GRADE": "C", "FL_NAME": "FLO", "SL_NAME": "SLE", "tL_NAME": "TLS", "award_flag": null, "NFSA/SFSA": null, "bankDetails": null}, {"UIN": "22204CC0001", "CNAME": "ABHIJEET SAHOO", "FNAME": "ANANTA CHARAN SAHOO", "MNAME": "AHALYA SAHOO", "SEX": "MALE", "DOB": "14/06/2006", "CAT": "OBC", "FL_TMRK": "87", "SL_TMRK": "52", "TL_TMRK": "100", "MTH_TMRK": "45", "GSC_TMRK": "69", "SSC_TMRK": "71", "GTOTAL": 424.0, "RES_GRADE": "B1", "FL_NAME": "FLO", "SL_NAME": "SLE", "tL_NAME": "TLS", "award_flag": null, "NFSA/SFSA": null, "bankDetails": null}, {"UIN": "22204CC0005", "CNAME": "ANKURA HO", "FNAME": "BISWANATH HO", "MNAME": "GURUBARI HO", "SEX": "MALE", "DOB": "02/06/2005", "CAT": "ST", "FL_TMRK": "66", "SL_TMRK": "34", "TL_TMRK": "95", "MTH_TMRK": "35", "GSC_TMRK": "51", "SSC_TMRK": "53", "GTOTAL": 334.0, "RES_GRADE": "C", "FL_NAME": "FLO", "SL_NAME": "SLE", "tL_NAME": "TLS", "award_flag": null, "NFSA/SFSA": null, "bankDetails": null}, {"UIN": "22204CC0006", "CNAME": "APARNNA BEHERA", "FNAME": "SUDARSAN BEHERA", "MNAME": "JYOTSNARANI BEHERA", "SEX": "FEMALE", "DOB": "05/04/2007", "CAT": "OBC", "FL_TMRK": "79", "SL_TMRK": "69", "TL_TMRK": "92", "MTH_TMRK": "55", "GSC_TMRK": "67", "SSC_TMRK": "62", "GTOTAL": 424.0, "RES_GRADE": "B1", "FL_NAME": "FLO", "SL_NAME": "SLE", "tL_NAME": "TLS", "award_flag": null, "NFSA/SFSA": null, "bankDetails": null}, {"UIN": "22204CC0007", "CNAME": "ARABINDA SAHOO", "FNAME": "RATNAKAR SAHOO", "MNAME": "AMBIKA SAHOO", "SEX": "MALE", "DOB": "08/10/2006", "CAT": "OBC", "FL_TMRK": "53", "SL_TMRK": "64", "TL_TMRK": "59", "MTH_TMRK": "49", "GSC_TMRK": "50", "SSC_TMRK": "50", "GTOTAL": 325.0, "RES_GRADE": "C", "FL_NAME": "FLO", "SL_NAME": "SLE", "tL_NAME": "TLS", "award_flag": null, "NFSA/SFSA": null, "bankDetails": null}, {"UIN": "22204CC0011", "CNAME": "BIDUSMITA SAHU", "FNAME": "DAMBARUDHARA SAHU", "MNAME": "JHUNURANI SAHU", "SEX": "FEMALE", "DOB": "11/01/2007", "CAT": "OBC", "FL_TMRK": "75", "SL_TMRK": "69", "TL_TMRK": "88", "MTH_TMRK": "56", "GSC_TMRK": "54", "SSC_TMRK": "70", "GTOTAL": 412.0, "RES_GRADE": "B2", "FL_NAME": "FLO", "SL_NAME": "SLE", "tL_NAME": "TLS", "award_flag": null, "NFSA/SFSA": null, "bankDetails": null}, {"UIN": "22204CC0012", "CNAME": "BIDYABATI SAHOO", "FNAME": "KESHAB CHANDRA SAHOO", "MNAME": "HEMALATA SAHOO", "SEX": "FEMALE", "DOB": "29/10/2006", "CAT": "OBC", "FL_TMRK": "83", "SL_TMRK": "57", "TL_TMRK": "68", "MTH_TMRK": "57", "GSC_TMRK": "57", "SSC_TMRK": "68", "GTOTAL": 390.0, "RES_GRADE": "B2", "FL_NAME": "FLO", "SL_NAME": "SLE", "tL_NAME": "TLS", "award_flag": null, "NFSA/SFSA": null, "bankDetails": null}, {"UIN": "22204CC0013", "CNAME": "BIJAYA KHATUA", "FNAME": "SIBA CHARAN KHATUA", "MNAME": "RITA KHATUA", "SEX": "MALE", "DOB": "01/04/2006", "CAT": "OBC", "FL_TMRK": "57", "SL_TMRK": "47", "TL_TMRK": "54", "MTH_TMRK": "47", "GSC_TMRK": "53", "SSC_TMRK": "51", "GTOTAL": 309.0, "RES_GRADE": "C", "FL_NAME": "FLO", "SL_NAME": "SLE", "tL_NAME": "TLS", "award_flag": null, "NFSA/SFSA": null, "bankDetails": null}, {"UIN": "22204CC0017", "CNAME": "BINI SAHOO", "FNAME": "BAIDHAR SAHOO", "MNAME": "BASANTI SAHOO", "SEX": "FEMALE", "DOB": "06/08/2007", "CAT": "OBC", "FL_TMRK": "88", "SL_TMRK": "62", "TL_TMRK": "81", "MTH_TMRK": "53", "GSC_TMRK": "35", "SSC_TMRK": "71", "GTOTAL": 390.0, "RES_GRADE": "B2", "FL_NAME": "FLO", "SL_NAME": "SLE", "tL_NAME": "TLS", "award_flag": null, "NFSA/SFSA": null, "bankDetails": null}, {"UIN": "22204CC0018", "CNAME": "BINOD KUMAR NAIK", "FNAME": "RAIMAN NAIK", "MNAME": "MAMATA NAIK", "SEX": "MALE", "DOB": "27/06/2007", "CAT": "ST", "FL_TMRK": "AB", "SL_TMRK": "AB", "TL_TMRK": "AB", "MTH_TMRK": "AB", "GSC_TMRK": "AB", "SSC_TMRK": "AB", "GTOTAL": 0.0, "RES_GRADE": "ABS", "FL_NAME": "FLO", "SL_NAME": "SLE", "tL_NAME": "TLS", "award_flag": null, "NFSA/SFSA": null, "bankDetails": null}, {"UIN": "22204CC0019", "CNAME": "BISWABANDITA SAHOO", "FNAME": "JAGANNATH SAHOO", "MNAME": "MAMATAMAYEE SAHOO", "SEX": "FEMALE", "DOB": "08/03/2007", "CAT": "OBC", "FL_TMRK": "91", "SL_TMRK": "65", "TL_TMRK": "87", "MTH_TMRK": "52", "GSC_TMRK": "65", "SSC_TMRK": "72", "GTOTAL": 432.0, "RES_GRADE": "B1", "FL_NAME": "FLO", "SL_NAME": "SLE", "tL_NAME": "TLS", "award_flag": null, "NFSA/SFSA": null, "bankDetails": null}, {"UIN": "22204CC0023", "CNAME": "DIBYASA BEHERA", "FNAME": "SARAT KUMAR BEHERA", "MNAME": "SRIMATI BEHERA", "SEX": "FEMALE", "DOB": "05/04/2007", "CAT": "OBC", "FL_TMRK": "98", "SL_TMRK": "92", "TL_TMRK": "98", "MTH_TMRK": "72", "GSC_TMRK": "87", "SSC_TMRK": "94", "GTOTAL": 541.0, "RES_GRADE": "A1", "FL_NAME": "FLO", "SL_NAME": "SLE", "tL_NAME": "TLS", "award_flag": null, "NFSA/SFSA": null, "bankDetails": null}, {"UIN": "22204CC0024", "CNAME": "HARIHAR SAHOO", "FNAME": "SANATAN SAHOO", "MNAME": "BASANTI SAHOO", "SEX": "MALE", "DOB": "02/03/2007", "CAT": "OBC", "FL_TMRK": "93", "SL_TMRK": "64", "TL_TMRK": "96", "MTH_TMRK": "71", "GSC_TMRK": "75", "SSC_TMRK": "75", "GTOTAL": 474.0, "RES_GRADE": "B1", "FL_NAME": "FLO", "SL_NAME": "SLE", "tL_NAME": "TLS", "award_flag": null, "NFSA/SFSA": null, "bankDetails": null}, {"UIN": "22204CC0025", "CNAME": "JAGABANDHU SAHOO", "FNAME": "MADHU SAHOO", "MNAME": "MALATI SAHOO", "SEX": "MALE", "DOB": "31/03/2006", "CAT": "OBC", "FL_TMRK": "87", "SL_TMRK": "86", "TL_TMRK": "91", "MTH_TMRK": "59", "GSC_TMRK": "79", "SSC_TMRK": "78", "GTOTAL": 480.0, "RES_GRADE": "A2", "FL_NAME": "FLO", "SL_NAME": "SLE", "tL_NAME": "TLS", "award_flag": null, "NFSA/SFSA": null, "bankDetails": null}, {"UIN": "22204CC0029", "CNAME": "KIRAN KUMAR SAHOO", "FNAME": "NIRANJAN SAHOO", "MNAME": "SASMITA SAHOO", "SEX": "MALE", "DOB": "14/07/2007", "CAT": "OBC", "FL_TMRK": "83", "SL_TMRK": "84", "TL_TMRK": "91", "MTH_TMRK": "62", "GSC_TMRK": "75", "SSC_TMRK": "82", "GTOTAL": 477.0, "RES_GRADE": "B1", "FL_NAME": "FLO", "SL_NAME": "SLE", "tL_NAME": "TLS", "award_flag": null, "NFSA/SFSA": null, "bankDetails": null}, {"UIN": "22204CC0030", "CNAME": "KRISHNARANI BIDHANI", "FNAME": "BASANTA KUMAR BINDHANI", "MNAME": "SANTILATA BINDHANI", "SEX": "FEMALE", "DOB": "20/02/2006", "CAT": "OBC", "FL_TMRK": "68", "SL_TMRK": "67", "TL_TMRK": "69", "MTH_TMRK": "48", "GSC_TMRK": "67", "SSC_TMRK": "76", "GTOTAL": 395.0, "RES_GRADE": "B2", "FL_NAME": "FLO", "SL_NAME": "SLE", "tL_NAME": "TLS", "award_flag": null, "NFSA/SFSA": null, "bankDetails": null}, {"UIN": "22204CC0031", "CNAME": "KUNAL SAMAL", "FNAME": "BASANTA KUMAR SAMAL", "MNAME": "SASMITA SAMAL", "SEX": "MALE", "DOB": "27/02/2007", "CAT": "OBC", "FL_TMRK": "69", "SL_TMRK": "56", "TL_TMRK": "62", "MTH_TMRK": "47", "GSC_TMRK": "57", "SSC_TMRK": "55", "GTOTAL": 346.0, "RES_GRADE": "C", "FL_NAME": "FLO", "SL_NAME": "SLE", "tL_NAME": "TLS", "award_flag": null, "NFSA/SFSA": null, "bankDetails": null}, {"UIN": "22204CC0035", "CNAME": "MANORANJAN SAHOO", "FNAME": "RAMESH CHANDRA SAHOO", "MNAME": "LILABATI SAHOO", "SEX": "MALE", "DOB": "21/11/2006", "CAT": "OBC", "FL_TMRK": "AB", "SL_TMRK": "AB", "TL_TMRK": "AB", "MTH_TMRK": "AB", "GSC_TMRK": "AB", "SSC_TMRK": "AB", "GTOTAL": 0.0, "RES_GRADE": "ABS", "FL_NAME": "FLO", "SL_NAME": "SLE", "tL_NAME": "TLS", "award_flag": null, "NFSA/SFSA": null, "bankDetails": null}, {"UIN": "22204CC0036", "CNAME": "NIRANJAN SAHOO", "FNAME": "DEBA SAHOO", "MNAME": "ASHANTI SAHOO", "SEX": "MALE", "DOB": "11/07/2006", "CAT": "OBC", "FL_TMRK": "84", "SL_TMRK": "61", "TL_TMRK": "96", "MTH_TMRK": "50", "GSC_TMRK": "60", "SSC_TMRK": "79", "GTOTAL": 430.0, "RES_GRADE": "B1", "FL_NAME": "FLO", "SL_NAME": "SLE", "tL_NAME": "TLS", "award_flag": null, "NFSA/SFSA": null, "bankDetails": null}, {"UIN": "22204CC0037", "CNAME": "PRINCE KUMAR SAHOO", "FNAME": "NARAYAN SAHOO", "MNAME": "SULOCHANA SAHOO", "SEX": "MALE", "DOB": "30/09/2006", "CAT": "OBC", "FL_TMRK": "60", "SL_TMRK": "32", "TL_TMRK": "61", "MTH_TMRK": "36", "GSC_TMRK": "56", "SSC_TMRK": "41", "GTOTAL": 286.0, "RES_GRADE": "D", "FL_NAME": "FLO", "SL_NAME": "SLE", "tL_NAME": "TLS", "award_flag": null, "NFSA/SFSA": null, "bankDetails": null}, {"UIN": "22204CC0041", "CNAME": "SARBESWAR SAHOO", "FNAME": "SARAN KUMAR SAHOO", "MNAME": "RUKMANI SAHOO", "SEX": "MALE", "DOB": "04/11/2006", "CAT": "OBC", "FL_TMRK": "83", "SL_TMRK": "40", "TL_TMRK": "91", "MTH_TMRK": "54", "GSC_TMRK": "47", "SSC_TMRK": "85", "GTOTAL": 400.0, "RES_GRADE": "B2", "FL_NAME": "FLO", "SL_NAME": "SLE", "tL_NAME": "TLS", "award_flag": null, "NFSA/SFSA": null, "bankDetails": null}, {"UIN": "22204CC0042", "CNAME": "SATYABRATA MALLICK", "FNAME": "SURENDRA KUMAR MALLICK", "MNAME": "RENUBALA MALLICK", "SEX": "MALE", "DOB": "31/08/2006", "CAT": "OBC", "FL_TMRK": "88", "SL_TMRK": "95", "TL_TMRK": "92", "MTH_TMRK": "72", "GSC_TMRK": "82", "SSC_TMRK": "86", "GTOTAL": 515.0, "RES_GRADE": "A2", "FL_NAME": "FLO", "SL_NAME": "SLE", "tL_NAME": "TLS", "award_flag": null, "NFSA/SFSA": null, "bankDetails": null}, {"UIN": "22204CC0043", "CNAME": "SATYAJIT BEHERA", "FNAME": "SARAN KUMAR BEHERA", "MNAME": "PARBATI BEHERA", "SEX": "MALE", "DOB": "23/03/2007", "CAT": "OBC", "FL_TMRK": "59", "SL_TMRK": "63", "TL_TMRK": "72", "MTH_TMRK": "58", "GSC_TMRK": "68", "SSC_TMRK": "65", "GTOTAL": 385.0, "RES_GRADE": "B2", "FL_NAME": "FLO", "SL_NAME": "SLE", "tL_NAME": "TLS", "award_flag": null, "NFSA/SFSA": null, "bankDetails": null}, {"UIN": "22204CC0044", "CNAME": "SATYARANJAN BEHERA", "FNAME": "ACHYUTANANDA BEHERA", "MNAME": "RENUBALA BEHERA", "SEX": "MALE", "DOB": "01/04/2007", "CAT": "OBC", "FL_TMRK": "99", "SL_TMRK": "98", "TL_TMRK": "98", "MTH_TMRK": "87", "GSC_TMRK": "93", "SSC_TMRK": "93", "GTOTAL": 568.0, "RES_GRADE": "A1", "FL_NAME": "FLO", "SL_NAME": "SLE", "tL_NAME": "TLS", "award_flag": null, "NFSA/SFSA": null, "bankDetails": null}, {"UIN": "22204CC0045", "CNAME": "SEEMA BEHERA", "FNAME": "KALANDI BEHERA", "MNAME": "KANAKA BEHERA", "SEX": "FEMALE", "DOB": "21/12/2006", "CAT": "OBC", "FL_TMRK": "62", "SL_TMRK": "48", "TL_TMRK": "86", "MTH_TMRK": "45", "GSC_TMRK": "57", "SSC_TMRK": "59", "GTOTAL": 357.0, "RES_GRADE": "C", "FL_NAME": "FLO", "SL_NAME": "SLE", "tL_NAME": "TLS", "award_flag": null, "NFSA/SFSA": null, "bankDetails": null}, {"UIN": "22204CC0046", "CNAME": "SHRABANI SAHU", "FNAME": "BUNU SAHOO", "MNAME": "BIMALA SAHU", "SEX": "FEMALE", "DOB": "16/05/2007", "CAT": "OBC", "FL_TMRK": "60", "SL_TMRK": "54", "TL_TMRK": "88", "MTH_TMRK": "50", "GSC_TMRK": "65", "SSC_TMRK": "60", "GTOTAL": 377.0, "RES_GRADE": "B2", "FL_NAME": "FLO", "SL_NAME": "SLE", "tL_NAME": "TLS", "award_flag": null, "NFSA/SFSA": null, "bankDetails": null}, {"UIN": "22204CC0050", "CNAME": "SMRUTIREKHA BHOL", "FNAME": "LAXMIDHAR BHOL", "MNAME": "SUMITRA BHOL", "SEX": "FEMALE", "DOB": "12/03/2006", "CAT": "OBC", "FL_TMRK": "80", "SL_TMRK": "73", "TL_TMRK": "87", "MTH_TMRK": "54", "GSC_TMRK": "67", "SSC_TMRK": "71", "GTOTAL": 432.0, "RES_GRADE": "B1", "FL_NAME": "FLO", "SL_NAME": "SLE", "tL_NAME": "TLS", "award_flag": null, "NFSA/SFSA": null, "bankDetails": null}, {"UIN": "22204CC0051", "CNAME": "SOMYAJIT SAMAL", "FNAME": "JACHINDRA KUMAR SAMAL", "MNAME": "MITARANI SAMAL", "SEX": "MALE", "DOB": "22/06/2006", "CAT": "OBC", "FL_TMRK": "92", "SL_TMRK": "44", "TL_TMRK": "99", "MTH_TMRK": "69", "GSC_TMRK": "64", "SSC_TMRK": "79", "GTOTAL": 447.0, "RES_GRADE": "B1", "FL_NAME": "FLO", "SL_NAME": "SLE", "tL_NAME": "TLS", "award_flag": null, "NFSA/SFSA": null, "bankDetails": null}, {"UIN": "22204CC0052", "CNAME": "SONALI NAIK", "FNAME": "MAGUNI CHARAN NAIK", "MNAME": "CHAGILI NAIK", "SEX": "FEMALE", "DOB": "20/03/2007", "CAT": "ST", "FL_TMRK": "47", "SL_TMRK": "38", "TL_TMRK": "40", "MTH_TMRK": "46", "GSC_TMRK": "47", "SSC_TMRK": "42", "GTOTAL": 260.0, "RES_GRADE": "D", "FL_NAME": "FLO", "SL_NAME": "SLE", "tL_NAME": "TLS", "award_flag": null, "NFSA/SFSA": null, "bankDetails": null}, {"UIN": "22204CC0056", "CNAME": "SUMAN KUMAR SAMAL", "FNAME": "SUDIP KUMAR SAMAL", "MNAME": "SASMITA SAMAL", "SEX": "MALE", "DOB": "03/02/2007", "CAT": "OBC", "FL_TMRK": "53", "SL_TMRK": "44", "TL_TMRK": "45", "MTH_TMRK": "47", "GSC_TMRK": "52", "SSC_TMRK": "48", "GTOTAL": 289.0, "RES_GRADE": "D", "FL_NAME": "FLO", "SL_NAME": "SLE", "tL_NAME": "TLS", "award_flag": null, "NFSA/SFSA": null, "bankDetails": null}, {"UIN": "22204CC0057", "CNAME": "SUNELI SAMAL", "FNAME": "GOPAL SAMAL", "MNAME": "JYOTSNA SAMAL", "SEX": "FEMALE", "DOB": "09/10/2006", "CAT": "OBC", "FL_TMRK": "53", "SL_TMRK": "38", "TL_TMRK": "58", "MTH_TMRK": "50", "GSC_TMRK": "51", "SSC_TMRK": "53", "GTOTAL": 303.0, "RES_GRADE": "C", "FL_NAME": "FLO", "SL_NAME": "SLE", "tL_NAME": "TLS", "award_flag": null, "NFSA/SFSA": null, "bankDetails": null}, {"UIN": "22204CC0058", "CNAME": "SUNITA DEHURI", "FNAME": "BINOD DEHURI", "MNAME": "BENGALATA DEHURI", "SEX": "FEMALE", "DOB": "04/02/2007", "CAT": "ST", "FL_TMRK": "51", "SL_TMRK": "39", "TL_TMRK": "47", "MTH_TMRK": "47", "GSC_TMRK": "46", "SSC_TMRK": "49", "GTOTAL": 279.0, "RES_GRADE": "D", "FL_NAME": "FLO", "SL_NAME": "SLE", "tL_NAME": "TLS", "award_flag": null, "NFSA/SFSA": null, "bankDetails": null}, {"UIN": "22204CC0062", "CNAME": "TRILOCHAN SAHOO", "FNAME": "SUDARSHAN SAHOO", "MNAME": "RENUBALA SAHOO", "SEX": "MALE", "DOB": "06/01/2007", "CAT": "OBC", "FL_TMRK": "91", "SL_TMRK": "89", "TL_TMRK": "100", "MTH_TMRK": "75", "GSC_TMRK": "90", "SSC_TMRK": "89", "GTOTAL": 534.0, "RES_GRADE": "A2", "FL_NAME": "FLO", "SL_NAME": "SLE", "tL_NAME": "TLS", "award_flag": null, "NFSA/SFSA": null, "bankDetails": null}, {"UIN": "22204CC0047", "CNAME": "SIKHA KAHATUA", "FNAME": "BANTHU KHATUA", "MNAME": "BASANTI KHATUA", "SEX": "FEMALE", "DOB": "15/07/2006", "CAT": "ST", "FL_TMRK": "AB", "SL_TMRK": "AB", "TL_TMRK": "AB", "MTH_TMRK": "AB", "GSC_TMRK": "AB", "SSC_TMRK": "AB", "GTOTAL": 0.0, "RES_GRADE": "ABS", "FL_NAME": "FLO", "SL_NAME": "SLE", "tL_NAME": "TLS", "award_flag": null, "NFSA/SFSA": null, "bankDetails": null}, {"UIN": "22204CC0048", "CNAME": "SIPUNU SAHOO", "FNAME": "PARIKHITA SAHOO", "MNAME": "BASANTI SAHOO", "SEX": "MALE", "DOB": "01/09/2006", "CAT": "OBC", "FL_TMRK": "38", "SL_TMRK": "51", "TL_TMRK": "47", "MTH_TMRK": "52", "GSC_TMRK": "45", "SSC_TMRK": "45", "GTOTAL": 278.0, "RES_GRADE": "D", "FL_NAME": "FLO", "SL_NAME": "SLE", "tL_NAME": "TLS", "award_flag": null, "NFSA/SFSA": null, "bankDetails": null}, {"UIN": "22204CC0049", "CNAME": "SMRUTIRANJAN SAHOO", "FNAME": "BHAGIRATHI SAHOO", "MNAME": "JHUNUBALA SAHOO", "SEX": "MALE", "DOB": "14/02/2007", "CAT": "OBC", "FL_TMRK": "66", "SL_TMRK": "80", "TL_TMRK": "86", "MTH_TMRK": "61", "GSC_TMRK": "70", "SSC_TMRK": "56", "GTOTAL": 419.0, "RES_GRADE": "B2", "FL_NAME": "FLO", "SL_NAME": "SLE", "tL_NAME": "TLS", "award_flag": null, "NFSA/SFSA": null, "bankDetails": null}, {"UIN": "22204CC0053", "CNAME": "SUBHAM KUMAR BEHERA", "FNAME": "BHARAT CHANDRA BEHERA", "MNAME": "RINARANI BEHERA", "SEX": "MALE", "DOB": "07/03/2006", "CAT": "OBC", "FL_TMRK": "60", "SL_TMRK": "60", "TL_TMRK": "80", "MTH_TMRK": "55", "GSC_TMRK": "57", "SSC_TMRK": "67", "GTOTAL": 379.0, "RES_GRADE": "B2", "FL_NAME": "FLO", "SL_NAME": "SLE", "tL_NAME": "TLS", "award_flag": null, "NFSA/SFSA": null, "bankDetails": null}, {"UIN": "22204CC0054", "CNAME": "SUBRAT DEHURI", "FNAME": "RAMESH DEHURI", "MNAME": "GOLAP DEHURI", "SEX": "MALE", "DOB": "12/04/2006", "CAT": "ST", "FL_TMRK": "46", "SL_TMRK": "48", "TL_TMRK": "48", "MTH_TMRK": "43", "GSC_TMRK": "56", "SSC_TMRK": "48", "GTOTAL": 289.0, "RES_GRADE": "D", "FL_NAME": "FLO", "SL_NAME": "SLE", "tL_NAME": "TLS", "award_flag": null, "NFSA/SFSA": null, "bankDetails": null}, {"UIN": "22204CC0055", "CNAME": "SUDAM NAIK", "FNAME": "KATHIA NAIK", "MNAME": "MITA NAIK", "SEX": "MALE", "DOB": "27/08/2006", "CAT": "ST", "FL_TMRK": "53", "SL_TMRK": "51", "TL_TMRK": "41", "MTH_TMRK": "43", "GSC_TMRK": "42", "SSC_TMRK": "46", "GTOTAL": 276.0, "RES_GRADE": "D", "FL_NAME": "FLO", "SL_NAME": "SLE", "tL_NAME": "TLS", "award_flag": null, "NFSA/SFSA": null, "bankDetails": null}, {"UIN": "22204CC0059", "CNAME": "SUPRIYA BEHERA", "FNAME": "SIBA BEHERA", "MNAME": "SABITRI BEHERA", "SEX": "FEMALE", "DOB": "04/03/2007", "CAT": "OBC", "FL_TMRK": "92", "SL_TMRK": "30", "TL_TMRK": "95", "MTH_TMRK": "66", "GSC_TMRK": "57", "SSC_TMRK": "45", "GTOTAL": 385.0, "RES_GRADE": "B2", "FL_NAME": "FLO", "SL_NAME": "SLE", "tL_NAME": "TLS", "award_flag": null, "NFSA/SFSA": null, "bankDetails": null}, {"UIN": "22204CC0060", "CNAME": "SWAGAT KUMAR SAHOO", "FNAME": "SANATAN SAHOO", "MNAME": "FULAMANI SAHOO", "SEX": "MALE", "DOB": "11/11/2006", "CAT": "OBC", "FL_TMRK": "78", "SL_TMRK": "31", "TL_TMRK": "91", "MTH_TMRK": "70", "GSC_TMRK": "57", "SSC_TMRK": "40", "GTOTAL": 367.0, "RES_GRADE": "B2", "FL_NAME": "FLO", "SL_NAME": "SLE", "tL_NAME": "TLS", "award_flag": null, "NFSA/SFSA": null, "bankDetails": null}, {"UIN": "22204CC0061", "CNAME": "TANMAYA SAHOO", "FNAME": "KANDURU SAHOO", "MNAME": "BHARATI SAHOO", "SEX": "MALE", "DOB": "30/03/2007", "CAT": "OBC", "FL_TMRK": "67", "SL_TMRK": "64", "TL_TMRK": "80", "MTH_TMRK": "53", "GSC_TMRK": "57", "SSC_TMRK": "61", "GTOTAL": 382.0, "RES_GRADE": "B2", "FL_NAME": "FLO", "SL_NAME": "SLE", "tL_NAME": "TLS", "award_flag": null, "NFSA/SFSA": null, "bankDetails": null}]}