{"blockName": "BANSPAL", "blockID": "2403007", "schoolID": "223CC", "schoolName": "U.G GOVT H/S JATRA", "udise": "21060203802", "studentCount": "37", "studentList": [{"UIN": "22223CC0001", "CNAME": "AJAY MAHARANA", "FNAME": "NILAMANI MAHARANA", "MNAME": "SUSHILA MAHARANA", "SEX": "MALE", "DOB": "08/03/2005", "CAT": "OBC", "FL_TMRK": "51", "SL_TMRK": "85", "TL_TMRK": "91", "MTH_TMRK": "53", "GSC_TMRK": "75", "SSC_TMRK": "75", "GTOTAL": 430.0, "RES_GRADE": "B1", "FL_NAME": "FLO", "SL_NAME": "SLE", "tL_NAME": "TLS", "award_flag": null, "NFSA/SFSA": null, "bankDetails": null}, {"UIN": "22223CC0002", "CNAME": "RANJAN KUMAR PRADHAN", "FNAME": "BAIRAGI PRADHAN", "MNAME": "BIMALA PRADHAN", "SEX": "MALE", "DOB": "15/03/2006", "CAT": "ST", "FL_TMRK": "57", "SL_TMRK": "80", "TL_TMRK": "90", "MTH_TMRK": "51", "GSC_TMRK": "77", "SSC_TMRK": "71", "GTOTAL": 426.0, "RES_GRADE": "B1", "FL_NAME": "FLO", "SL_NAME": "SLE", "tL_NAME": "TLS", "award_flag": null, "NFSA/SFSA": null, "bankDetails": null}, {"UIN": "22223CC0003", "CNAME": "CHUMUKI DEHURY", "FNAME": "ANAND DEHURY", "MNAME": "KUNI DEHURY", "SEX": "FEMALE", "DOB": "22/04/2004", "CAT": "ST", "FL_TMRK": "61", "SL_TMRK": "63", "TL_TMRK": "77", "MTH_TMRK": "47", "GSC_TMRK": "71", "SSC_TMRK": "62", "GTOTAL": 381.0, "RES_GRADE": "B2", "FL_NAME": "FLO", "SL_NAME": "SLE", "tL_NAME": "TLS", "award_flag": null, "NFSA/SFSA": null, "bankDetails": null}, {"UIN": "22223CC0007", "CNAME": "BHADRASEN PRADHAN", "FNAME": "GOUTAM PRADHAN", "MNAME": "FAGUNI PRADHAN", "SEX": "MALE", "DOB": "12/01/2001", "CAT": "ST", "FL_TMRK": "AB", "SL_TMRK": "AB", "TL_TMRK": "AB", "MTH_TMRK": "AB", "GSC_TMRK": "AB", "SSC_TMRK": "AB", "GTOTAL": 0.0, "RES_GRADE": "ABS", "FL_NAME": "FLO", "SL_NAME": "SLE", "tL_NAME": "TLS", "award_flag": null, "NFSA/SFSA": null, "bankDetails": null}, {"UIN": "22223CC0008", "CNAME": "AIBAN MANDAL", "FNAME": "BIBHISAN MANDAL", "MNAME": "LOCHANI MANDAL", "SEX": "MALE", "DOB": "04/04/2004", "CAT": "ST", "FL_TMRK": "42", "SL_TMRK": "67", "TL_TMRK": "82", "MTH_TMRK": "46", "GSC_TMRK": "73", "SSC_TMRK": "63", "GTOTAL": 373.0, "RES_GRADE": "B2", "FL_NAME": "FLO", "SL_NAME": "SLE", "tL_NAME": "TLS", "award_flag": null, "NFSA/SFSA": null, "bankDetails": null}, {"UIN": "22223CC0009", "CNAME": "SAROJ PRADHAN", "FNAME": "GURUDEV PRADHAN", "MNAME": "BIMALA PRADHAN", "SEX": "MALE", "DOB": "20/08/2005", "CAT": "ST", "FL_TMRK": "34", "SL_TMRK": "77", "TL_TMRK": "89", "MTH_TMRK": "57", "GSC_TMRK": "73", "SSC_TMRK": "65", "GTOTAL": 395.0, "RES_GRADE": "B2", "FL_NAME": "FLO", "SL_NAME": "SLE", "tL_NAME": "TLS", "award_flag": null, "NFSA/SFSA": null, "bankDetails": null}, {"UIN": "22223CC0015", "CNAME": "LAXMAN MAHAKUD", "FNAME": "SUDARSAN MAHAKUD", "MNAME": "KAIN MAHAKUD", "SEX": "MALE", "DOB": "04/08/2006", "CAT": "OBC", "FL_TMRK": "44", "SL_TMRK": "48", "TL_TMRK": "65", "MTH_TMRK": "49", "GSC_TMRK": "65", "SSC_TMRK": "57", "GTOTAL": 328.0, "RES_GRADE": "C", "FL_NAME": "FLO", "SL_NAME": "SLE", "tL_NAME": "TLS", "award_flag": null, "NFSA/SFSA": null, "bankDetails": null}, {"UIN": "22223CC0016", "CNAME": "SANKHALI DEHURY", "FNAME": "MADAN DEHURY", "MNAME": "SASHI DEHURY", "SEX": "MALE", "DOB": "22/01/2006", "CAT": "ST", "FL_TMRK": "37", "SL_TMRK": "44", "TL_TMRK": "77", "MTH_TMRK": "33", "GSC_TMRK": "60", "SSC_TMRK": "42", "GTOTAL": 293.0, "RES_GRADE": "D", "FL_NAME": "FLO", "SL_NAME": "SLE", "tL_NAME": "TLS", "award_flag": null, "NFSA/SFSA": null, "bankDetails": null}, {"UIN": "22223CC0017", "CNAME": "SUJATA BARIK", "FNAME": "BIDYADHAR BARIK", "MNAME": "MALLI BARIK", "SEX": "FEMALE", "DOB": "25/05/2005", "CAT": "OBC", "FL_TMRK": "58", "SL_TMRK": "78", "TL_TMRK": "88", "MTH_TMRK": "56", "GSC_TMRK": "76", "SSC_TMRK": "82", "GTOTAL": 438.0, "RES_GRADE": "B1", "FL_NAME": "FLO", "SL_NAME": "SLE", "tL_NAME": "TLS", "award_flag": null, "NFSA/SFSA": null, "bankDetails": null}, {"UIN": "22223CC0023", "CNAME": "PRABINA KUMAR MALIK", "FNAME": "AKULA MALIK", "MNAME": "SREEMATI MALIK", "SEX": "MALE", "DOB": "07/06/2003", "CAT": "ST", "FL_TMRK": "48", "SL_TMRK": "65", "TL_TMRK": "75", "MTH_TMRK": "52", "GSC_TMRK": "76", "SSC_TMRK": "61", "GTOTAL": 377.0, "RES_GRADE": "B2", "FL_NAME": "FLO", "SL_NAME": "SLE", "tL_NAME": "TLS", "award_flag": null, "NFSA/SFSA": null, "bankDetails": null}, {"UIN": "22223CC0024", "CNAME": "SUMITRA PRADHAN", "FNAME": "PADU PRADHAN", "MNAME": "SRIMATI PRADHAN", "SEX": "FEMALE", "DOB": "24/06/1998", "CAT": "ST", "FL_TMRK": "AB", "SL_TMRK": "AB", "TL_TMRK": "AB", "MTH_TMRK": "AB", "GSC_TMRK": "AB", "SSC_TMRK": "AB", "GTOTAL": 0.0, "RES_GRADE": "ABS", "FL_NAME": "FLO", "SL_NAME": "SLE", "tL_NAME": "TLS", "award_flag": null, "NFSA/SFSA": null, "bankDetails": null}, {"UIN": "22223CC0025", "CNAME": "KARTIKA GIRI", "FNAME": "SUKANTA GIRI", "MNAME": "MASURI GIRI", "SEX": "MALE", "DOB": "23/05/2003", "CAT": "ST", "FL_TMRK": "43", "SL_TMRK": "75", "TL_TMRK": "85", "MTH_TMRK": "49", "GSC_TMRK": "79", "SSC_TMRK": "67", "GTOTAL": 398.0, "RES_GRADE": "B2", "FL_NAME": "FLO", "SL_NAME": "SLE", "tL_NAME": "TLS", "award_flag": null, "NFSA/SFSA": null, "bankDetails": null}, {"UIN": "22223CC0033", "CNAME": "ARUN GIRI", "FNAME": "GOKUL GIRI", "MNAME": "AMULI GIRI", "SEX": "MALE", "DOB": "02/09/2005", "CAT": "ST", "FL_TMRK": "67", "SL_TMRK": "77", "TL_TMRK": "80", "MTH_TMRK": "58", "GSC_TMRK": "78", "SSC_TMRK": "70", "GTOTAL": 430.0, "RES_GRADE": "B1", "FL_NAME": "FLO", "SL_NAME": "SLE", "tL_NAME": "TLS", "award_flag": null, "NFSA/SFSA": null, "bankDetails": null}, {"UIN": "22223CC0034", "CNAME": "PHULAMANI SAUNTA", "FNAME": "SHUKA SAUNTA", "MNAME": "BILEI SAUNTA", "SEX": "FEMALE", "DOB": "05/04/2003", "CAT": "ST", "FL_TMRK": "52", "SL_TMRK": "81", "TL_TMRK": "79", "MTH_TMRK": "55", "GSC_TMRK": "75", "SSC_TMRK": "60", "GTOTAL": 402.0, "RES_GRADE": "B2", "FL_NAME": "FLO", "SL_NAME": "SLE", "tL_NAME": "TLS", "award_flag": null, "NFSA/SFSA": null, "bankDetails": null}, {"UIN": "22223CC0035", "CNAME": "UMESH GIRI", "FNAME": "BIDYADHAR GIRI", "MNAME": "JAMUNA GIRI", "SEX": "MALE", "DOB": "17/03/2005", "CAT": "ST", "FL_TMRK": "AB", "SL_TMRK": "AB", "TL_TMRK": "AB", "MTH_TMRK": "AB", "GSC_TMRK": "AB", "SSC_TMRK": "AB", "GTOTAL": 0.0, "RES_GRADE": "ABS", "FL_NAME": "FLO", "SL_NAME": "SLE", "tL_NAME": "TLS", "award_flag": null, "NFSA/SFSA": null, "bankDetails": null}, {"UIN": "22223CC0004", "CNAME": "DAKTAR DEHURY", "FNAME": "BALARAM DEHURY", "MNAME": "DROUPADI DEHURY", "SEX": "MALE", "DOB": "25/03/2004", "CAT": "ST", "FL_TMRK": "55", "SL_TMRK": "69", "TL_TMRK": "77", "MTH_TMRK": "52", "GSC_TMRK": "74", "SSC_TMRK": "50", "GTOTAL": 377.0, "RES_GRADE": "B2", "FL_NAME": "FLO", "SL_NAME": "SLE", "tL_NAME": "TLS", "award_flag": null, "NFSA/SFSA": null, "bankDetails": null}, {"UIN": "22223CC0005", "CNAME": "SASMITA BARIK", "FNAME": "RAMESH BARIK", "MNAME": "MALATI BARIK", "SEX": "FEMALE", "DOB": "10/09/2005", "CAT": "OBC", "FL_TMRK": "47", "SL_TMRK": "78", "TL_TMRK": "89", "MTH_TMRK": "59", "GSC_TMRK": "75", "SSC_TMRK": "66", "GTOTAL": 414.0, "RES_GRADE": "B2", "FL_NAME": "FLO", "SL_NAME": "SLE", "tL_NAME": "TLS", "award_flag": null, "NFSA/SFSA": null, "bankDetails": null}, {"UIN": "22223CC0006", "CNAME": "BRUNDABAN DHIBAR", "FNAME": "PARADESHI DHIBAR", "MNAME": "SAKUNTALA DHIBAR", "SEX": "MALE", "DOB": "20/08/2005", "CAT": "SC", "FL_TMRK": "40", "SL_TMRK": "67", "TL_TMRK": "74", "MTH_TMRK": "45", "GSC_TMRK": "69", "SSC_TMRK": "57", "GTOTAL": 352.0, "RES_GRADE": "C", "FL_NAME": "FLO", "SL_NAME": "SLE", "tL_NAME": "TLS", "award_flag": null, "NFSA/SFSA": null, "bankDetails": null}, {"UIN": "22223CC0010", "CNAME": "KABIBAR THAKUR", "FNAME": "MANU THAKUR", "MNAME": "SUNDARI THAKUR", "SEX": "MALE", "DOB": "31/08/2006", "CAT": "ST", "FL_TMRK": "70", "SL_TMRK": "83", "TL_TMRK": "90", "MTH_TMRK": "46", "GSC_TMRK": "76", "SSC_TMRK": "79", "GTOTAL": 444.0, "RES_GRADE": "B1", "FL_NAME": "FLO", "SL_NAME": "SLE", "tL_NAME": "TLS", "award_flag": null, "NFSA/SFSA": null, "bankDetails": null}, {"UIN": "22223CC0011", "CNAME": "AJIT KUMAR DHIBAR", "FNAME": "BIRANCHI DHIBAR", "MNAME": "TULEI DHIBAR", "SEX": "MALE", "DOB": "22/11/2006", "CAT": "SC", "FL_TMRK": "AB", "SL_TMRK": "AB", "TL_TMRK": "AB", "MTH_TMRK": "AB", "GSC_TMRK": "AB", "SSC_TMRK": "AB", "GTOTAL": 0.0, "RES_GRADE": "ABS", "FL_NAME": "FLO", "SL_NAME": "SLE", "tL_NAME": "TLS", "award_flag": null, "NFSA/SFSA": null, "bankDetails": null}, {"UIN": "22223CC0014", "CNAME": "NIRASHA MUNDA", "FNAME": "BAIGRAM MUNDA", "MNAME": "JANA MUNDA", "SEX": "FEMALE", "DOB": "13/10/2000", "CAT": "ST", "FL_TMRK": "AB", "SL_TMRK": "AB", "TL_TMRK": "AB", "MTH_TMRK": "AB", "GSC_TMRK": "AB", "SSC_TMRK": "AB", "GTOTAL": 0.0, "RES_GRADE": "ABS", "FL_NAME": "FLO", "SL_NAME": "SLE", "tL_NAME": "TLS", "award_flag": null, "NFSA/SFSA": null, "bankDetails": null}, {"UIN": "22223CC0019", "CNAME": "GURU MUNDA", "FNAME": "PURNA MUNDA", "MNAME": "NABATI MUNDA", "SEX": "MALE", "DOB": "13/04/2005", "CAT": "ST", "FL_TMRK": "45", "SL_TMRK": "75", "TL_TMRK": "82", "MTH_TMRK": "56", "GSC_TMRK": "69", "SSC_TMRK": "63", "GTOTAL": 390.0, "RES_GRADE": "B2", "FL_NAME": "FLO", "SL_NAME": "SLE", "tL_NAME": "TLS", "award_flag": null, "NFSA/SFSA": null, "bankDetails": null}, {"UIN": "22223CC0020", "CNAME": "RAYA MUNDA", "FNAME": "KIRSAN MUNDA", "MNAME": "SAMBARI MUNDA", "SEX": "MALE", "DOB": "22/03/2005", "CAT": "ST", "FL_TMRK": "AB", "SL_TMRK": "AB", "TL_TMRK": "AB", "MTH_TMRK": "AB", "GSC_TMRK": "AB", "SSC_TMRK": "AB", "GTOTAL": 0.0, "RES_GRADE": "ABS", "FL_NAME": "FLO", "SL_NAME": "SLE", "tL_NAME": "TLS", "award_flag": null, "NFSA/SFSA": null, "bankDetails": null}, {"UIN": "22223CC0021", "CNAME": "CHARAN GIRI", "FNAME": "NILAMBARA GIRI", "MNAME": "BASANTI GIRI", "SEX": "MALE", "DOB": "15/04/2006", "CAT": "ST", "FL_TMRK": "AB", "SL_TMRK": "AB", "TL_TMRK": "AB", "MTH_TMRK": "AB", "GSC_TMRK": "AB", "SSC_TMRK": "AB", "GTOTAL": 0.0, "RES_GRADE": "ABS", "FL_NAME": "FLO", "SL_NAME": "SLE", "tL_NAME": "TLS", "award_flag": null, "NFSA/SFSA": null, "bankDetails": null}, {"UIN": "22223CC0027", "CNAME": "SUKUMANI MUNDA", "FNAME": "GANESWAR MUNDA", "MNAME": "DASHAMA MUNDA", "SEX": "FEMALE", "DOB": "01/02/2007", "CAT": "ST", "FL_TMRK": "30", "SL_TMRK": "55", "TL_TMRK": "64", "MTH_TMRK": "40", "GSC_TMRK": "64", "SSC_TMRK": "42", "GTOTAL": 295.0, "RES_GRADE": "D", "FL_NAME": "FLO", "SL_NAME": "SLE", "tL_NAME": "TLS", "award_flag": null, "NFSA/SFSA": null, "bankDetails": null}, {"UIN": "22223CC0028", "CNAME": "LAXMI MUNDA", "FNAME": "LAXMAN MUNDA", "MNAME": "SAPANI MUNDA", "SEX": "FEMALE", "DOB": "01/10/2005", "CAT": "ST", "FL_TMRK": "31", "SL_TMRK": "64", "TL_TMRK": "71", "MTH_TMRK": "46", "GSC_TMRK": "69", "SSC_TMRK": "37", "GTOTAL": 318.0, "RES_GRADE": "C", "FL_NAME": "FLO", "SL_NAME": "SLE", "tL_NAME": "TLS", "award_flag": null, "NFSA/SFSA": null, "bankDetails": null}, {"UIN": "22223CC0032", "CNAME": "KALIA MUNDA", "FNAME": "NIRANJAN MUNDA", "MNAME": "BASUMUNI MUNDA", "SEX": "MALE", "DOB": "22/01/2005", "CAT": "ST", "FL_TMRK": "32", "SL_TMRK": "38", "TL_TMRK": "61", "MTH_TMRK": "43", "GSC_TMRK": "52", "SSC_TMRK": "53", "GTOTAL": 279.0, "RES_GRADE": "D", "FL_NAME": "FLO", "SL_NAME": "SLE", "tL_NAME": "TLS", "award_flag": null, "NFSA/SFSA": null, "bankDetails": null}, {"UIN": "22223CC0036", "CNAME": "UMESH CHANDRA DEHURY", "FNAME": "SUBARNA DEHURY", "MNAME": "MALAPA DEHURY", "SEX": "MALE", "DOB": "06/07/2007", "CAT": "ST", "FL_TMRK": "AB", "SL_TMRK": "AB", "TL_TMRK": "AB", "MTH_TMRK": "AB", "GSC_TMRK": "AB", "SSC_TMRK": "AB", "GTOTAL": 0.0, "RES_GRADE": "ABS", "FL_NAME": "FLO", "SL_NAME": "SLE", "tL_NAME": "TLS", "award_flag": null, "NFSA/SFSA": null, "bankDetails": null}, {"UIN": "22223CC0037", "CNAME": "GOBINDA MUNDA", "FNAME": "KUSUNA MUNDA", "MNAME": "ASALI MUNDA", "SEX": "MALE", "DOB": "15/01/2005", "CAT": "ST", "FL_TMRK": "AB", "SL_TMRK": "AB", "TL_TMRK": "AB", "MTH_TMRK": "AB", "GSC_TMRK": "AB", "SSC_TMRK": "AB", "GTOTAL": 0.0, "RES_GRADE": "ABS", "FL_NAME": "FLO", "SL_NAME": "SLE", "tL_NAME": "TLS", "award_flag": null, "NFSA/SFSA": null, "bankDetails": null}, {"UIN": "22223CC0038", "CNAME": "BIKASH DHIBAR", "FNAME": "GURUCHARAN DHIBAR", "MNAME": "SAILANI DHIBAR", "SEX": "MALE", "DOB": "21/05/2005", "CAT": "SC", "FL_TMRK": "49", "SL_TMRK": "62", "TL_TMRK": "80", "MTH_TMRK": "52", "GSC_TMRK": "60", "SSC_TMRK": "53", "GTOTAL": 356.0, "RES_GRADE": "C", "FL_NAME": "FLO", "SL_NAME": "SLE", "tL_NAME": "TLS", "award_flag": null, "NFSA/SFSA": null, "bankDetails": null}, {"UIN": "22223CC0039", "CNAME": "SUBAS MAHAKUD", "FNAME": "HARI MAHAKUD", "MNAME": "JANAKI MAHAKUD", "SEX": "MALE", "DOB": "25/01/2006", "CAT": "OBC", "FL_TMRK": "62", "SL_TMRK": "71", "TL_TMRK": "79", "MTH_TMRK": "55", "GSC_TMRK": "69", "SSC_TMRK": "66", "GTOTAL": 402.0, "RES_GRADE": "B2", "FL_NAME": "FLO", "SL_NAME": "SLE", "tL_NAME": "TLS", "award_flag": null, "NFSA/SFSA": null, "bankDetails": null}, {"UIN": "22223CC0040", "CNAME": "SHRIDHAR SAUNTA", "FNAME": "JHARA SAUNTA", "MNAME": "GURUBARI SAUNTA", "SEX": "MALE", "DOB": "28/08/2005", "CAT": "ST", "FL_TMRK": "AB", "SL_TMRK": "AB", "TL_TMRK": "AB", "MTH_TMRK": "AB", "GSC_TMRK": "AB", "SSC_TMRK": "AB", "GTOTAL": 0.0, "RES_GRADE": "ABS", "FL_NAME": "FLO", "SL_NAME": "SLE", "tL_NAME": "TLS", "award_flag": null, "NFSA/SFSA": null, "bankDetails": null}, {"UIN": "22223CC0042", "CNAME": "PRASANTA KUMAR MAHAKUD", "FNAME": "MURALI MAHAKUD", "MNAME": "JEMA MAHAKUD", "SEX": "MALE", "DOB": "28/03/2004", "CAT": "OBC", "FL_TMRK": "34", "SL_TMRK": "50", "TL_TMRK": "70", "MTH_TMRK": "43", "GSC_TMRK": "52", "SSC_TMRK": "51", "GTOTAL": 300.0, "RES_GRADE": "C", "FL_NAME": "FLO", "SL_NAME": "SLE", "tL_NAME": "TLS", "award_flag": null, "NFSA/SFSA": null, "bankDetails": null}, {"UIN": "22223CC0049", "CNAME": "HAPPY GIRI", "FNAME": "PARESH CHANDRA GIRI", "MNAME": "KASTURI GIRI", "SEX": "FEMALE", "DOB": "17/04/2005", "CAT": "ST", "FL_TMRK": "36", "SL_TMRK": "30", "TL_TMRK": "31", "MTH_TMRK": "47", "GSC_TMRK": "38", "SSC_TMRK": "33", "GTOTAL": 215.0, "RES_GRADE": "E", "FL_NAME": "FLO", "SL_NAME": "SLE", "tL_NAME": "TLS", "award_flag": null, "NFSA/SFSA": null, "bankDetails": null}, {"UIN": "22223CC0043", "CNAME": "PRAKASH KUMAR GIRI", "FNAME": "NILAKANTHA GIRI", "MNAME": "MARISA GIRI", "SEX": "MALE", "DOB": "17/04/2005", "CAT": "ST", "FL_TMRK": "AB", "SL_TMRK": "AB", "TL_TMRK": "AB", "MTH_TMRK": "AB", "GSC_TMRK": "AB", "SSC_TMRK": "AB", "GTOTAL": 0.0, "RES_GRADE": "ABS", "FL_NAME": "FLO", "SL_NAME": "SLE", "tL_NAME": "TLS", "award_flag": null, "NFSA/SFSA": null, "bankDetails": null}, {"UIN": "22223CC0045", "CNAME": "BANKU MAHAKUD", "FNAME": "DESHA MAHAKUD", "MNAME": "PADMINI MAHAKUD", "SEX": "MALE", "DOB": "05/02/2006", "CAT": "OBC", "FL_TMRK": "AB", "SL_TMRK": "AB", "TL_TMRK": "AB", "MTH_TMRK": "AB", "GSC_TMRK": "AB", "SSC_TMRK": "AB", "GTOTAL": 0.0, "RES_GRADE": "ABS", "FL_NAME": "FLO", "SL_NAME": "SLE", "tL_NAME": "TLS", "award_flag": null, "NFSA/SFSA": null, "bankDetails": null}, {"UIN": "22223CC0048", "CNAME": "KADILA DEHURY", "FNAME": "GANGADHARA DEHURY", "MNAME": "HEMA DEHURY", "SEX": "FEMALE", "DOB": "13/03/2004", "CAT": "ST", "FL_TMRK": "56", "SL_TMRK": "74", "TL_TMRK": "91", "MTH_TMRK": "54", "GSC_TMRK": "74", "SSC_TMRK": "75", "GTOTAL": 424.0, "RES_GRADE": "B1", "FL_NAME": "FLO", "SL_NAME": "SLE", "tL_NAME": "TLS", "award_flag": null, "NFSA/SFSA": null, "bankDetails": null}]}